cast_bootstrap5/__init__.py
cast_bootstrap5/apps.py
cast_bootstrap5/static/cast_bootstrap5/css/bootstrap5/bootstrap.min.css
cast_bootstrap5/static/cast_bootstrap5/css/bootstrap5/bootstrap.min.css.map
cast_bootstrap5/static/cast_bootstrap5/css/bootstrap5/cast.css
cast_bootstrap5/static/cast_bootstrap5/js/bootstrap5/bootstrap.bundle.min.js
cast_bootstrap5/static/cast_bootstrap5/js/bootstrap5/bootstrap.bundle.min.js.map
cast_bootstrap5/static/cast_bootstrap5/js/htmx.min.js
cast_bootstrap5/static/cast_bootstrap5/js/image-gallery-bs5.js
cast_bootstrap5/static/cast_bootstrap5/js/image-gallery-bs5_with_prefetch.js
cast_bootstrap5/static/cast_bootstrap5/js/jquery/jquery-3.7.1.min.js
cast_bootstrap5/static/cast_bootstrap5/vite/main-Zfu5LElp.js
cast_bootstrap5/static/cast_bootstrap5/vite/manifest.json
cast_bootstrap5/static/cast_bootstrap5/vite/podlovePlayer-B-VbvJ8r.js
cast_bootstrap5/templates/cast/bootstrap5/400.html
cast_bootstrap5/templates/cast/bootstrap5/403.html
cast_bootstrap5/templates/cast/bootstrap5/403_csrf.html
cast_bootstrap5/templates/cast/bootstrap5/404.html
cast_bootstrap5/templates/cast/bootstrap5/500.html
cast_bootstrap5/templates/cast/bootstrap5/_list_of_posts_and_paging_controls.html
cast_bootstrap5/templates/cast/bootstrap5/base.html
cast_bootstrap5/templates/cast/bootstrap5/blog_list_of_posts.html
cast_bootstrap5/templates/cast/bootstrap5/episode.html
cast_bootstrap5/templates/cast/bootstrap5/gallery.html
cast_bootstrap5/templates/cast/bootstrap5/gallery_htmx.html
cast_bootstrap5/templates/cast/bootstrap5/gallery_modal.html
cast_bootstrap5/templates/cast/bootstrap5/pagination.html
cast_bootstrap5/templates/cast/bootstrap5/post.html
cast_bootstrap5/templates/cast/bootstrap5/post_body.html
cast_bootstrap5/templates/cast/bootstrap5/select_theme.html
cast_bootstrap5/templates/cast/bootstrap5/transcript.html
cast_bootstrap5-0.0.71.dist-info/WHEEL
cast_bootstrap5-0.0.71.dist-info/METADATA
cast_bootstrap5-0.0.71.dist-info/RECORD
